{
    "page_title": "Integration",
    "partner": {
        "klaviyo": "Klaviyo",
        "mailchimp": "Mailchimp"
    },
    "status_enable": "Enable",
    "status_disable": "Disable",
    "klaviyo_description": "Marketing automation for Email Marketing, SMS & CDP",
    "mailchimp_description": "The email and SMS marketing automations platform that helps you boost opens, clicks and sales",
    "cta_integrate": "Integrate",
    "enable_integration": "Enable integration",
    "enable_to_connect_warning": "Please enable the integration to proceed with the connection",
    "connect": "Connect",
    "connected": "Connected",
    "api_key_label": "API key",
    "api_key_placeholder": "Enter API key",
    "api_key_invalid": "Invalid API key, please re-enter or use another key",
    "klaviyo": {
        "page_title": "Klaviyo Integration",
        "section_title": "Klaviyo Integration",
        "section_description": "Synchronize customer profiles, create lists & segments, and set up email campaign with Klaviyo",
        "connect_section_title": "Connect to Klaviyo",
        "modal_title": "Connect to Klaviyo",
        "modal_instructions": "Follow <1>this guide</1> to get Klaviyo's API key. Then enter API key and click Connect.",
        "verify": "Verify",
        "toast_api_valid": "API key is valid.",
        "toast_sync_ok": "Sync data successfully.",
        "toast_sync_fail": "Sync data failed, please try again."
    },
    "mailchimp": {
        "page_title": "Mailchimp Integration",
        "section_title": "Mailchimp Integration",
        "section_description": "Synchronize contacts, and set up email campaigns and automations with Mailchimp",
        "connect_section_title": "Connect to Mailchimp",
        "modal_title": "Connect to Mailchimp",
        "modal_instructions": "Follow <1>this guide</1> to get Mailchimp's API key. Then enter API key and click Connect.",
        "audience_id_label": "Audience id",
        "audience_id_placeholder": "Audience id",
        "audience_id_required": "Please enter Audience ID",
        "audience_id_invalid": "Invalid Audience ID, please re-enter or use another Audience ID",
        "api_key_required": "Please enter API key",
        "sync": "Sync",
        "syncing": "Syncing...",
        "batch_status_prefix": "Batch {{batchId}} is {{status}}.",
        "batch_progress_title": "Batch progress",
        "total_operations": "Total operations: {{count}}",
        "finished": "Finished: {{count}}",
        "errored": "Errored: {{count}}",
        "finished_operations": "Finished operations",
        "errored_operations": "Errored operations",
        "view_response": "View Mailchimp batch response",
        "error_unknown": "Unknown error",
        "batch_failed": "Mailchimp batch failed",
        "batch_status_error": "Failed to get Mailchimp batch status",
        "sync_failed_retry": "Sync data failed, please try again."
    }
}
